{
  "kind": "singleType",
  "collectionName": "website_communities",
  "info": {
    "singularName": "website-community",
    "pluralName": "website-communities",
    "displayName": "Website Community"
  },
  "options": {
    "draftAndPublish": false
  },
  "pluginOptions": {
    "i18n": {
      "localized": true
    }
  },
  "attributes": {
    "image_desktop_1": {
      "allowedTypes": [
        "images"
      ],
      "type": "media",
      "multiple": false,
      "pluginOptions": {
        "i18n": {
          "localized": true
        }
      }
    },
    "image_mobile_1": {
      "allowedTypes": [
        "images"
      ],
      "type": "media",
      "multiple": false,
      "pluginOptions": {
        "i18n": {
          "localized": true
        }
      }
    }
  }
}
